ticketing_service_core/__init__.py
ticketing_service_core/events/__init__.py
ticketing_service_core/events/consumer.py
ticketing_service_core/events/consumer_exception.py
ticketing_service_core/events/event_handler.py
ticketing_service_core/events/missing_resource_exception.py
ticketing_service_core/orm/__init__.py
ticketing_service_core/orm/search_filters.py
ticketing_service_core/orm/sql_administrator.py
ticketing_service_core/schema/__init__.py
ticketing_service_core/schema/advertisement.py
ticketing_service_core/schema/auth_key.py
ticketing_service_core/schema/category.py
ticketing_service_core/schema/empty.py
ticketing_service_core/schema/identifier.py
ticketing_service_core/schema/rpc_fields.py
ticketing_service_core/schema/time.py
ticketing_service_core-0.1.3.dist-info/METADATA
ticketing_service_core-0.1.3.dist-info/WHEEL
ticketing_service_core-0.1.3.dist-info/top_level.txt
ticketing_service_core-0.1.3.dist-info/RECORD
