Metadata-Version: 2.4
Name: ticketing_service_core
Version: 0.1.3
Summary: Python library providing utility functions to TickeTing's event-driven python microservices
Author-email: Sven James <dev@ticketingevents.com>
Classifier: Programming Language :: Python :: 3
Classifier: Operating System :: OS Independent
Requires-Python: >=3.9
Requires-Dist: pika
Requires-Dist: pyyaml
Requires-Dist: jsonschema
Requires-Dist: loguru
Requires-Dist: alembic
Requires-Dist: sqlalchemy
Requires-Dist: mysqlclient
